setup.py
EasyDialogs/__init__.py
easydialogs_gtk.egg-info/PKG-INFO
easydialogs_gtk.egg-info/SOURCES.txt
easydialogs_gtk.egg-info/dependency_links.txt
easydialogs_gtk.egg-info/requires.txt
easydialogs_gtk.egg-info/top_level.txt