Metadata-Version: 1.0
Name: easydialogs-gtk
Version: 0.1
Summary: EasyDialogs for Linux
Home-page: http://code.google.com/p/easydialogs-gtk/
Author: Lukas Sedenka
Author-email: sedenkal@gmail.com
License: http://www.opensource.org/licenses/bsd-license.php
Keywords: dialog gtk pygtk python
Platform: any
